vlc.py
python_vlc-3.0.21201.dist-info/COPYING
python_vlc-3.0.21201.dist-info/METADATA
python_vlc-3.0.21201.dist-info/WHEEL
python_vlc-3.0.21201.dist-info/top_level.txt
python_vlc-3.0.21201.dist-info/RECORD
