Metadata-Version: 2.1
Name: python-vlc
Version: 3.0.21201
Summary: VLC bindings for python.
Author-email: Olivier Aubert <contact@olivieraubert.net>
Maintainer-email: Olivier Aubert <contact@olivieraubert.net>
License: LGPL-2.1+
Project-URL: Homepage, https://wiki.videolan.org/PythonBinding
Project-URL: Documentation, https://www.olivieraubert.net/vlc/python-ctypes/doc/
Project-URL: Repository, https://github.com/oaubert/python-vlc.git
Project-URL: Alternate repository, https://git.videolan.org/?p=vlc/bindings/python.git;a=summary
Project-URL: Bug Tracker, https://github.com/oaubert/python-vlc/issues
Keywords: vlc,video
Classifier: Development Status :: 5 - Production/Stable
Classifier: Intended Audience :: Developers
Classifier: License :: OSI Approved :: GNU Lesser General Public License v2 or later (LGPLv2+)
Classifier: Operating System :: MacOS :: MacOS X
Classifier: Operating System :: Microsoft :: Windows
Classifier: Operating System :: POSIX :: Linux
Classifier: Operating System :: POSIX :: Other
Classifier: Programming Language :: Python
Classifier: Programming Language :: Python :: 2
Classifier: Programming Language :: Python :: 3
Classifier: Topic :: Multimedia
Classifier: Topic :: Multimedia :: Sound/Audio
Classifier: Topic :: Multimedia :: Video
License-File: COPYING
